Workbook

Sheet Data Vendors
A1: Vendor Name | B1: Specific Dataset Name | C1: What Data It Provides | D1: Cost Estimate (Annual) | E1: Timeliness | F1: Relevance to Energy Investing (1-10) | G1: Timeliness (1-10) | H1: Implementation (1-10) | I1: Total Score | J1: Tier
A2: Privateer | B2: Oil & Gas Operations Intelligence | C2: Satellite + AIS data for oilfield, pipeline, terminal, refinery, methane, fracking monitoring | D2: $30,000+ – $100,000+ | E2: Real-time | F2: 9 | G2: 10 | H2: 7 | I2: =F2+G2+H2 -> 26 | J2: =IF(I2>=24,"Tier 1",IF(I2>=15,"Tier 2","Tier 3")) -> Tier 1
A3: Kpler | B3: Crude Oil & LNG Supply Intelligence | C3: Real-time global crude inventory (tank-level), LNG inventory by country, tanker tracking, refinery runs (900+ refineries), refined product trade flows, commodity prices, supply/demand analytics | D3: $150K-$400K+ | E3: Real-time/Daily | F3: 10 | G3: 9 | H3: 8 | I3: =F3+G3+H3 -> 27 | J3: =IF(I3>=24,"Tier 1",IF(I3>=15,"Tier 2","Tier 3")) -> Tier 1
A4: MarineTraffic | B4: Global Vessel Tracking & Port Activity | C4: Real-time AIS tracking (13,000+ receivers), port call events, ship-to-ship transfers, vessel compliance data, historical movements (since 2010), predictive ETAs | D4: Essential: €1K/yr (1 vessel), Enterprise: Custom | E4: Near real-time (satellite signal dependent) | F4: 7 | G4: 8 | H4: 8 | I4: =F4+G4+H4 -> 23 | J4: =IF(I4>=24,"Tier 1",IF(I4>=15,"Tier 2","Tier 3")) -> Tier 2
A5: Wood Mackenzie | B5: Energy Market Intelligence & Analytics | C5: Upstream oil/gas data, LNG market insights, refinery analytics, emissions tracking, energy transition data, power & renewables intelligence, market reports | D5: Enterprise: Custom (Est. $100K+/yr for subscriptions | E5: Daily/Weekly reports | F5: 8 | G5: 6 | H5: 7 | I5: =F5+G5+H5 -> 21 | J5: =IF(I5>=24,"Tier 1",IF(I5>=15,"Tier 2","Tier 3")) -> Tier 2
A6: Enverus | B6: Energy Operations & Production Intelligence | C6: Real-time rig counts, drilling activity, production capacity, operations data, supply chain analytics, financial benchmarking across 98% USA producers | D6: Custom/Enterprise (Estimated $100K+/yr) | E6: Real-time | F6: 8 | G6: 9 | H6: 8 | I6: =F6+G6+H6 -> 25 | J6: =IF(I6>=24,"Tier 1",IF(I6>=15,"Tier 2","Tier 3")) -> Tier 1
A7: IEA (International Energy Agency) | B7: Global Energy Statistics & Forecasts | C7: Production forecasts, supply/demand balances, energy outlook reports, policy database, 5-10 year projections across 64% global energy production | D7: Subscription/Custom (Estimated $50K-$150K/yr) | E7: Monthly/Quarterly reports | F7: 7 | G7: 5 | H7: 6 | I7: =F7+G7+H7 -> 18 | J7: =IF(I7>=24,"Tier 1",IF(I7>=15,"Tier 2","Tier 3")) -> Tier 2
A8: Kayrros | B8: Energy Market Intelligence (Satellite-Based) | C8: Crude oil inventory tracking, production forecasting, flaring/emissions detection, LNG outages, renewable construction monitoring, carbon allowance tracking, industrial energy demand | D8: Custom/Enterprise (Estimated $150K-$500K+/yr) | E8: Near real-time | F8: 9 | G8: 9 | H8: 7 | I8: =F8+G8+H8 -> 25 | J8: =IF(I8>=24,"Tier 1",IF(I8>=15,"Tier 2","Tier 3")) -> Tier 1
A9: YES Energy | B9: Power Market Operating System | C9: Real-time LMP (electricity prices), grid frequency data, renewable generation, demand forecasting, FTR data, 1,100+ data sources, 15+ years historical | D9: Custom/Enterprise (Estimated $100K-$300K+/yr) | E9: Real-time (minute-by-minute) | F9: 8 | G9: 10 | H9: 8 | I9: =F9+G9+H9 -> 26 | J9: =IF(I9>=24,"Tier 1",IF(I9>=15,"Tier 2","Tier 3")) -> Tier 1
A10: Vortexa | B10: Energy Shipping & Trading Intelligence | C10: Global oil & gas vessel tracking, shipping flows, freight analytics, inventory data, trading market signals | D10: (Estimate $100K-$300K+/yr) | E10: Real-time | F10: 8 | G10: 9 | H10: 8 | I10: =F10+G10+H10 -> 25 | J10: =IF(I10>=24,"Tier 1",IF(I10>=15,"Tier 2","Tier 3")) -> Tier 1

Sheet Dashboard
B2: ⚡ Energy Data Vendor Intelligence Dashboard | I2: 🔽 Filter by Tier
B3: KEY PERFORMANCE INDICATORS | I3: Select Tier:
B4: AVG TOTAL SCORE | D4: TIER 1 VENDORS | F4: AVG RELEVANCE SCORE | I4: All
B5: =AVERAGE('Data Vendors'!I2:I10) -> 24 | D5: =COUNTIF('Data Vendors'!J2:J10,"Tier 1") -> 6 | F5: =AVERAGE('Data Vendors'!F2:F10) -> 8.2222222 | I5: =IF(I4="All","Showing all "&COUNTA('Data Vendors'!A2:A10)&" vendors","Showing "&COUNTIF('Data Vendors'!J2:J10,I4)&" "&I4&" vendors") -> Showing all 9 vendors
B6: out of 30 pts | D6: of 9 vendors | F6: energy investing (/10) | I6: FILTERED AVG SCORE
B7: VENDOR COMPARISON
B8: VENDOR | C8: DATASET | D8: RELEVANCE | E8: TIMELINESS | F8: IMPL. | G8: SCORE | H8: TIER
B9: {=IFERROR(IF($I$4="All",INDEX('Data Vendors'!A$2:A$10,1),INDEX(_xlfn._xlws.FILTER('Data Vendors'!A2:A10,'Data Vendors'!J2:J10=$I$4),1)),"")} -> Privateer | C9: {=IFERROR(IF($I$4="All",INDEX('Data Vendors'!B$2:B$10,1),INDEX(_xlfn._xlws.FILTER('Data Vendors'!B2:B10,'Data Vendors'!J2:J10=$I$4),1)),"")} -> Oil & Gas Operations Intelligence | D9: {=IFERROR(IF($I$4="All",INDEX('Data Vendors'!F$2:F$10,1),INDEX(_xlfn._xlws.FILTER('Data Vendors'!F2:F10,'Data Vendors'!J2:J10=$I$4),1)),"")} -> 9 | E9: {=IFERROR(IF($I$4="All",INDEX('Data Vendors'!G$2:G$10,1),INDEX(_xlfn._xlws.FILTER('Data Vendors'!G2:G10,'Data Vendors'!J2:J10=$I$4),1)),"")} -> 10 | F9: {=IFERROR(IF($I$4="All",INDEX('Data Vendors'!H$2:H$10,1),INDEX(_xlfn._xlws.FILTER('Data Vendors'!H2:H10,'Data Vendors'!J2:J10=$I$4),1)),"")} -> 7 | G9: {=IFERROR(IF($I$4="All",INDEX('Data Vendors'!I$2:I$10,1),INDEX(_xlfn._xlws.FILTER('Data Vendors'!I2:I10,'Data Vendors'!J2:J10=$I$4),1)),"")} -> 26 | H9: {=IFERROR(IF($I$4="All",INDEX('Data Vendors'!J$2:J$10,1),INDEX(_xlfn._xlws.FILTER('Data Vendors'!J2:J10,'Data Vendors'!J2:J10=$I$4),1)),"")} -> Tier 1
B10: {=IFERROR(IF($I$4="All",INDEX('Data Vendors'!A$2:A$10,2),INDEX(_xlfn._xlws.FILTER('Data Vendors'!A2:A10,'Data Vendors'!J2:J10=$I$4),2)),"")} -> Kpler | C10: {=IFERROR(IF($I$4="All",INDEX('Data Vendors'!B$2:B$10,2),INDEX(_xlfn._xlws.FILTER('Data Vendors'!B2:B10,'Data Vendors'!J2:J10=$I$4),2)),"")} -> Crude Oil & LNG Supply Intelligence | D10: {=IFERROR(IF($I$4="All",INDEX('Data Vendors'!F$2:F$10,2),INDEX(_xlfn._xlws.FILTER('Data Vendors'!F2:F10,'Data Vendors'!J2:J10=$I$4),2)),"")} -> 10 | E10: {=IFERROR(IF($I$4="All",INDEX('Data Vendors'!G$2:G$10,2),INDEX(_xlfn._xlws.FILTER('Data Vendors'!G2:G10,'Data Vendors'!J2:J10=$I$4),2)),"")} -> 9 | F10: {=IFERROR(IF($I$4="All",INDEX('Data Vendors'!H$2:H$10,2),INDEX(_xlfn._xlws.FILTER('Data Vendors'!H2:H10,'Data Vendors'!J2:J10=$I$4),2)),"")} -> 8 | G10: {=IFERROR(IF($I$4="All",INDEX('Data Vendors'!I$2:I$10,2),INDEX(_xlfn._xlws.FILTER('Data Vendors'!I2:I10,'Data Vendors'!J2:J10=$I$4),2)),"")} -> 27 | H10: {=IFERROR(IF($I$4="All",INDEX('Data Vendors'!J$2:J$10,2),INDEX(_xlfn._xlws.FILTER('Data Vendors'!J2:J10,'Data Vendors'!J2:J10=$I$4),2)),"")} -> Tier 1
B11: {=IFERROR(IF($I$4="All",INDEX('Data Vendors'!A$2:A$10,3),INDEX(_xlfn._xlws.FILTER('Data Vendors'!A2:A10,'Data Vendors'!J2:J10=$I$4),3)),"")} -> MarineTraffic | C11: {=IFERROR(IF($I$4="All",INDEX('Data Vendors'!B$2:B$10,3),INDEX(_xlfn._xlws.FILTER('Data Vendors'!B2:B10,'Data Vendors'!J2:J10=$I$4),3)),"")} -> Global Vessel Tracking & Port Activity | D11: {=IFERROR(IF($I$4="All",INDEX('Data Vendors'!F$2:F$10,3),INDEX(_xlfn._xlws.FILTER('Data Vendors'!F2:F10,'Data Vendors'!J2:J10=$I$4),3)),"")} -> 7 | E11: {=IFERROR(IF($I$4="All",INDEX('Data Vendors'!G$2:G$10,3),INDEX(_xlfn._xlws.FILTER('Data Vendors'!G2:G10,'Data Vendors'!J2:J10=$I$4),3)),"")} -> 8 | F11: {=IFERROR(IF($I$4="All",INDEX('Data Vendors'!H$2:H$10,3),INDEX(_xlfn._xlws.FILTER('Data Vendors'!H2:H10,'Data Vendors'!J2:J10=$I$4),3)),"")} -> 8 | G11: {=IFERROR(IF($I$4="All",INDEX('Data Vendors'!I$2:I$10,3),INDEX(_xlfn._xlws.FILTER('Data Vendors'!I2:I10,'Data Vendors'!J2:J10=$I$4),3)),"")} -> 23 | H11: {=IFERROR(IF($I$4="All",INDEX('Data Vendors'!J$2:J$10,3),INDEX(_xlfn._xlws.FILTER('Data Vendors'!J2:J10,'Data Vendors'!J2:J10=$I$4),3)),"")} -> Tier 2
B12: {=IFERROR(IF($I$4="All",INDEX('Data Vendors'!A$2:A$10,4),INDEX(_xlfn._xlws.FILTER('Data Vendors'!A2:A10,'Data Vendors'!J2:J10=$I$4),4)),"")} -> Wood Mackenzie | C12: {=IFERROR(IF($I$4="All",INDEX('Data Vendors'!B$2:B$10,4),INDEX(_xlfn._xlws.FILTER('Data Vendors'!B2:B10,'Data Vendors'!J2:J10=$I$4),4)),"")} -> Energy Market Intelligence & Analytics | D12: {=IFERROR(IF($I$4="All",INDEX('Data Vendors'!F$2:F$10,4),INDEX(_xlfn._xlws.FILTER('Data Vendors'!F2:F10,'Data Vendors'!J2:J10=$I$4),4)),"")} -> 8 | E12: {=IFERROR(IF($I$4="All",INDEX('Data Vendors'!G$2:G$10,4),INDEX(_xlfn._xlws.FILTER('Data Vendors'!G2:G10,'Data Vendors'!J2:J10=$I$4),4)),"")} -> 6 | F12: {=IFERROR(IF($I$4="All",INDEX('Data Vendors'!H$2:H$10,4),INDEX(_xlfn._xlws.FILTER('Data Vendors'!H2:H10,'Data Vendors'!J2:J10=$I$4),4)),"")} -> 7 | G12: {=IFERROR(IF($I$4="All",INDEX('Data Vendors'!I$2:I$10,4),INDEX(_xlfn._xlws.FILTER('Data Vendors'!I2:I10,'Data Vendors'!J2:J10=$I$4),4)),"")} -> 21 | H12: {=IFERROR(IF($I$4="All",INDEX('Data Vendors'!J$2:J$10,4),INDEX(_xlfn._xlws.FILTER('Data Vendors'!J2:J10,'Data Vendors'!J2:J10=$I$4),4)),"")} -> Tier 2
B13: {=IFERROR(IF($I$4="All",INDEX('Data Vendors'!A$2:A$10,5),INDEX(_xlfn._xlws.FILTER('Data Vendors'!A2:A10,'Data Vendors'!J2:J10=$I$4),5)),"")} -> Enverus | C13: {=IFERROR(IF($I$4="All",INDEX('Data Vendors'!B$2:B$10,5),INDEX(_xlfn._xlws.FILTER('Data Vendors'!B2:B10,'Data Vendors'!J2:J10=$I$4),5)),"")} -> Energy Operations & Production Intelligence | D13: {=IFERROR(IF($I$4="All",INDEX('Data Vendors'!F$2:F$10,5),INDEX(_xlfn._xlws.FILTER('Data Vendors'!F2:F10,'Data Vendors'!J2:J10=$I$4),5)),"")} -> 8 | E13: {=IFERROR(IF($I$4="All",INDEX('Data Vendors'!G$2:G$10,5),INDEX(_xlfn._xlws.FILTER('Data Vendors'!G2:G10,'Data Vendors'!J2:J10=$I$4),5)),"")} -> 9 | F13: {=IFERROR(IF($I$4="All",INDEX('Data Vendors'!H$2:H$10,5),INDEX(_xlfn._xlws.FILTER('Data Vendors'!H2:H10,'Data Vendors'!J2:J10=$I$4),5)),"")} -> 8 | G13: {=IFERROR(IF($I$4="All",INDEX('Data Vendors'!I$2:I$10,5),INDEX(_xlfn._xlws.FILTER('Data Vendors'!I2:I10,'Data Vendors'!J2:J10=$I$4),5)),"")} -> 25 | H13: {=IFERROR(IF($I$4="All",INDEX('Data Vendors'!J$2:J$10,5),INDEX(_xlfn._xlws.FILTER('Data Vendors'!J2:J10,'Data Vendors'!J2:J10=$I$4),5)),"")} -> Tier 1
B14: {=IFERROR(IF($I$4="All",INDEX('Data Vendors'!A$2:A$10,6),INDEX(_xlfn._xlws.FILTER('Data Vendors'!A2:A10,'Data Vendors'!J2:J10=$I$4),6)),"")} -> IEA (International Energy Agency) | C14: {=IFERROR(IF($I$4="All",INDEX('Data Vendors'!B$2:B$10,6),INDEX(_xlfn._xlws.FILTER('Data Vendors'!B2:B10,'Data Vendors'!J2:J10=$I$4),6)),"")} -> Global Energy Statistics & Forecasts | D14: {=IFERROR(IF($I$4="All",INDEX('Data Vendors'!F$2:F$10,6),INDEX(_xlfn._xlws.FILTER('Data Vendors'!F2:F10,'Data Vendors'!J2:J10=$I$4),6)),"")} -> 7 | E14: {=IFERROR(IF($I$4="All",INDEX('Data Vendors'!G$2:G$10,6),INDEX(_xlfn._xlws.FILTER('Data Vendors'!G2:G10,'Data Vendors'!J2:J10=$I$4),6)),"")} -> 5 | F14: {=IFERROR(IF($I$4="All",INDEX('Data Vendors'!H$2:H$10,6),INDEX(_xlfn._xlws.FILTER('Data Vendors'!H2:H10,'Data Vendors'!J2:J10=$I$4),6)),"")} -> 6 | G14: {=IFERROR(IF($I$4="All",INDEX('Data Vendors'!I$2:I$10,6),INDEX(_xlfn._xlws.FILTER('Data Vendors'!I2:I10,'Data Vendors'!J2:J10=$I$4),6)),"")} -> 18 | H14: {=IFERROR(IF($I$4="All",INDEX('Data Vendors'!J$2:J$10,6),INDEX(_xlfn._xlws.FILTER('Data Vendors'!J2:J10,'Data Vendors'!J2:J10=$I$4),6)),"")} -> Tier 2
B15: {=IFERROR(IF($I$4="All",INDEX('Data Vendors'!A$2:A$10,7),INDEX(_xlfn._xlws.FILTER('Data Vendors'!A2:A10,'Data Vendors'!J2:J10=$I$4),7)),"")} -> Kayrros | C15: {=IFERROR(IF($I$4="All",INDEX('Data Vendors'!B$2:B$10,7),INDEX(_xlfn._xlws.FILTER('Data Vendors'!B2:B10,'Data Vendors'!J2:J10=$I$4),7)),"")} -> Energy Market Intelligence (Satellite-Based) | D15: {=IFERROR(IF($I$4="All",INDEX('Data Vendors'!F$2:F$10,7),INDEX(_xlfn._xlws.FILTER('Data Vendors'!F2:F10,'Data Vendors'!J2:J10=$I$4),7)),"")} -> 9 | E15: {=IFERROR(IF($I$4="All",INDEX('Data Vendors'!G$2:G$10,7),INDEX(_xlfn._xlws.FILTER('Data Vendors'!G2:G10,'Data Vendors'!J2:J10=$I$4),7)),"")} -> 9 | F15: {=IFERROR(IF($I$4="All",INDEX('Data Vendors'!H$2:H$10,7),INDEX(_xlfn._xlws.FILTER('Data Vendors'!H2:H10,'Data Vendors'!J2:J10=$I$4),7)),"")} -> 7 | G15: {=IFERROR(IF($I$4="All",INDEX('Data Vendors'!I$2:I$10,7),INDEX(_xlfn._xlws.FILTER('Data Vendors'!I2:I10,'Data Vendors'!J2:J10=$I$4),7)),"")} -> 25 | H15: {=IFERROR(IF($I$4="All",INDEX('Data Vendors'!J$2:J$10,7),INDEX(_xlfn._xlws.FILTER('Data Vendors'!J2:J10,'Data Vendors'!J2:J10=$I$4),7)),"")} -> Tier 1
B16: {=IFERROR(IF($I$4="All",INDEX('Data Vendors'!A$2:A$10,8),INDEX(_xlfn._xlws.FILTER('Data Vendors'!A2:A10,'Data Vendors'!J2:J10=$I$4),8)),"")} -> YES Energy | C16: {=IFERROR(IF($I$4="All",INDEX('Data Vendors'!B$2:B$10,8),INDEX(_xlfn._xlws.FILTER('Data Vendors'!B2:B10,'Data Vendors'!J2:J10=$I$4),8)),"")} -> Power Market Operating System | D16: {=IFERROR(IF($I$4="All",INDEX('Data Vendors'!F$2:F$10,8),INDEX(_xlfn._xlws.FILTER('Data Vendors'!F2:F10,'Data Vendors'!J2:J10=$I$4),8)),"")} -> 8 | E16: {=IFERROR(IF($I$4="All",INDEX('Data Vendors'!G$2:G$10,8),INDEX(_xlfn._xlws.FILTER('Data Vendors'!G2:G10,'Data Vendors'!J2:J10=$I$4),8)),"")} -> 10 | F16: {=IFERROR(IF($I$4="All",INDEX('Data Vendors'!H$2:H$10,8),INDEX(_xlfn._xlws.FILTER('Data Vendors'!H2:H10,'Data Vendors'!J2:J10=$I$4),8)),"")} -> 8 | G16: {=IFERROR(IF($I$4="All",INDEX('Data Vendors'!I$2:I$10,8),INDEX(_xlfn._xlws.FILTER('Data Vendors'!I2:I10,'Data Vendors'!J2:J10=$I$4),8)),"")} -> 26 | H16: {=IFERROR(IF($I$4="All",INDEX('Data Vendors'!J$2:J$10,8),INDEX(_xlfn._xlws.FILTER('Data Vendors'!J2:J10,'Data Vendors'!J2:J10=$I$4),8)),"")} -> Tier 1
B17: {=IFERROR(IF($I$4="All",INDEX('Data Vendors'!A$2:A$10,9),INDEX(_xlfn._xlws.FILTER('Data Vendors'!A2:A10,'Data Vendors'!J2:J10=$I$4),9)),"")} -> Vortexa | C17: {=IFERROR(IF($I$4="All",INDEX('Data Vendors'!B$2:B$10,9),INDEX(_xlfn._xlws.FILTER('Data Vendors'!B2:B10,'Data Vendors'!J2:J10=$I$4),9)),"")} -> Energy Shipping & Trading Intelligence | D17: {=IFERROR(IF($I$4="All",INDEX('Data Vendors'!F$2:F$10,9),INDEX(_xlfn._xlws.FILTER('Data Vendors'!F2:F10,'Data Vendors'!J2:J10=$I$4),9)),"")} -> 8 | E17: {=IFERROR(IF($I$4="All",INDEX('Data Vendors'!G$2:G$10,9),INDEX(_xlfn._xlws.FILTER('Data Vendors'!G2:G10,'Data Vendors'!J2:J10=$I$4),9)),"")} -> 9 | F17: {=IFERROR(IF($I$4="All",INDEX('Data Vendors'!H$2:H$10,9),INDEX(_xlfn._xlws.FILTER('Data Vendors'!H2:H10,'Data Vendors'!J2:J10=$I$4),9)),"")} -> 8 | G17: {=IFERROR(IF($I$4="All",INDEX('Data Vendors'!I$2:I$10,9),INDEX(_xlfn._xlws.FILTER('Data Vendors'!I2:I10,'Data Vendors'!J2:J10=$I$4),9)),"")} -> 25 | H17: {=IFERROR(IF($I$4="All",INDEX('Data Vendors'!J$2:J$10,9),INDEX(_xlfn._xlws.FILTER('Data Vendors'!J2:J10,'Data Vendors'!J2:J10=$I$4),9)),"")} -> Tier 1
